<Updates>
 <ApplicationName>{AnyApplication}</ApplicationName>
 <ApplicationVersion>1.0.0</ApplicationVersion>
 <Checksum>true</Checksum>
 <SHA1>eca6667d0f8be2fbd62a589e98be4e42b606c806</SHA1>
 <MetadataName>2023-10-09-0159_meta.7z</MetadataName>
 <PackageUpdate>
  <Name>de.spotifyenhancer.main</Name>
  <DisplayName>SpotifyEnhancer</DisplayName>
  <Description>Install SpotifyEnhancer 1.4.3, a programm to automatically restart Spotify when advertisement is played.</Description>
  <Version>1.4.3</Version>
  <Default>true</Default>
  <ReleaseDate>2023-10-08</ReleaseDate>
  <Script>installscript.qs</Script>
  <UpdateFile OS="Any" UncompressedSize="55398166" CompressedSize="16456410"/>
  <DownloadableArchives>generic.7z,iconengines.7z,imageformats.7z,networkinformation.7z,platforms.7z,styles.7z,tls.7z,content.7z</DownloadableArchives>
  <Licenses>
   <License name="GNU GENERAL PUBLIC LICENSE Version 3, 29 June 2007" file="license.txt"/>
  </Licenses>
  <Operations>
   <Operation name="Extract">
    <Argument>@TargetDir@/bin/</Argument>
   </Operation>
  </Operations>
  <SHA1>527056e53bfa121c415c5f516e91d4d8aaf155dd</SHA1>
 </PackageUpdate>
</Updates>
